gspread/__init__.py
gspread/auth.py
gspread/cell.py
gspread/client.py
gspread/exceptions.py
gspread/spreadsheet.py
gspread/urls.py
gspread/utils.py
gspread/worksheet.py
gspread-5.8.0.dist-info/LICENSE.txt
gspread-5.8.0.dist-info/METADATA
gspread-5.8.0.dist-info/WHEEL
gspread-5.8.0.dist-info/top_level.txt
gspread-5.8.0.dist-info/RECORD
