Metadata-Version: 2.1
Name: gspread
Version: 5.8.0
Summary: Google Spreadsheets Python API
Home-page: https://github.com/burnash/gspread
Author: Anton Burnashev
Author-email: fuss.here@gmail.com
Maintainer: Alexandre Lavigne
Maintainer-email: lavigne958@gmail.com
License: MIT
Keywords: spreadsheets,google-spreadsheets
Classifier: Programming Language :: Python
Classifier: Programming Language :: Python :: 3
Classifier: Programming Language :: Python :: 3.7
Classifier: Programming Language :: Python :: 3.8
Classifier: Programming Language :: Python :: 3.9
Classifier: License :: OSI Approved :: MIT License
Classifier: Operating System :: OS Independent
Classifier: Development Status :: 5 - Production/Stable
Classifier: Intended Audience :: Developers
Classifier: Intended Audience :: End Users/Desktop
Classifier: Intended Audience :: Science/Research
Classifier: Topic :: Office/Business :: Financial :: Spreadsheet
Classifier: Topic :: Software Development :: Libraries :: Python Modules
Requires-Python: >=3.6, !=3.0.*, !=3.1.*, !=3.2.*, !=3.3.*
License-File: LICENSE.txt
